Metadata-Version: 2.1
Name: sentry-processor
Version: 0.0.1
Summary: sentry event processor for protecting sensitive infos
Home-page: https://github.com/laiyongtao/sentry-processor
Author: laiyongtao
Author-email: laiyongtao6908@163.com
License: BSD-3-Clause License
Keywords: sentry,processor,sensitive,filter
Platform: all
Classifier: Programming Language :: Python
